cellcharter/__init__.py
cellcharter/_utils.py
cellcharter/_constants/_pkg_constants.py
cellcharter/datasets/__init__.py
cellcharter/datasets/_dataset.py
cellcharter/gr/__init__.py
cellcharter/gr/_aggr.py
cellcharter/gr/_build.py
cellcharter/gr/_group.py
cellcharter/gr/_nhood.py
cellcharter/gr/_utils.py
cellcharter/pl/__init__.py
cellcharter/pl/_autok.py
cellcharter/pl/_group.py
cellcharter/pl/_nhood.py
cellcharter/pl/_shape.py
cellcharter/pl/_utils.py
cellcharter/tl/__init__.py
cellcharter/tl/_autok.py
cellcharter/tl/_gmm.py
cellcharter/tl/_shape.py
cellcharter/tl/_trvae.py
cellcharter/tl/_utils.py
cellcharter-0.3.5.dist-info/METADATA
cellcharter-0.3.5.dist-info/WHEEL
cellcharter-0.3.5.dist-info/licenses/LICENSE
cellcharter-0.3.5.dist-info/RECORD
