Metadata-Version: 2.4
Name: cellcharter
Version: 0.3.5
Summary: A Python package for the identification, characterization and comparison of spatial clusters from spatial -omics data.
Project-URL: Documentation, https://cellcharter.readthedocs.io/
Project-URL: Source, https://github.com/CSOgroup/cellcharter
Project-URL: Home-page, https://github.com/CSOgroup/cellcharter
Author: CSO group
Maintainer-email: Marco Varrone <marco.varrone@unil.ch>
License: BSD 3-Clause License
License-File: LICENSE
Requires-Python: <3.14,>=3.10
Requires-Dist: anndata
Requires-Dist: rasterio
Requires-Dist: scikit-learn
Requires-Dist: session-info
Requires-Dist: sknw
Requires-Dist: spatialdata
Requires-Dist: spatialdata-plot
Requires-Dist: squidpy>=1.6.3
Requires-Dist: torchgmm>=0.1.2
Provides-Extra: dev
Requires-Dist: pre-commit; extra == 'dev'
Requires-Dist: twine>=4.0.2; extra == 'dev'
Provides-Extra: doc
Requires-Dist: docutils!=0.18.*,!=0.19.*,>=0.8; extra == 'doc'
Requires-Dist: ipykernel; extra == 'doc'
Requires-Dist: ipython; extra == 'doc'
Requires-Dist: myst-nb>=1.1.0; extra == 'doc'
Requires-Dist: sphinx-autodoc-typehints; extra == 'doc'
Requires-Dist: sphinx-book-theme>=1.0.0; extra == 'doc'
Requires-Dist: sphinx-copybutton; extra == 'doc'
Requires-Dist: sphinx-design; extra == 'doc'
Requires-Dist: sphinx>=4; extra == 'doc'
Requires-Dist: sphinxcontrib-bibtex>=1.0.0; extra == 'doc'
Requires-Dist: sphinxext-opengraph; extra == 'doc'
Provides-Extra: proteomics
Requires-Dist: scarches; extra == 'proteomics'
Provides-Extra: test
Requires-Dist: pytest; extra == 'test'
Requires-Dist: pytest-cov; extra == 'test'
Provides-Extra: transcriptomics
Requires-Dist: scvi-tools; extra == 'transcriptomics'
